aurorapy/__init__.py
aurorapy/client.py
aurorapy/defaults.py
aurorapy/mapping.py
aurorapy-0.2.7.dist-info/LICENSE.txt
aurorapy-0.2.7.dist-info/METADATA
aurorapy-0.2.7.dist-info/WHEEL
aurorapy-0.2.7.dist-info/top_level.txt
aurorapy-0.2.7.dist-info/RECORD
