Metadata-Version: 2.1
Name: aurorapy
Version: 0.2.7
Summary: Python implementation of Aurora Protocol
Home-page: https://gitlab.com/energievalsabbia/aurorapy
Author: E.Va Energie Valsabbia
Author-email: it@energievalsabbia.it
Maintainer: Claudio Catterina
Maintainer-email: ccatterina@energievalsabbia.it
License: MIT
Platform: UNKNOWN
Classifier: Development Status :: 4 - Beta
Classifier: Intended Audience :: Developers
Classifier: Operating System :: OS Independent
Classifier: License :: OSI Approved :: MIT License
Classifier: Environment :: Console
Classifier: Programming Language :: Python
Requires-Dist: pyserial (>=3.2.1)
Requires-Dist: future (>=0.16.0)
